db1/__init__.py
db1/_client.py
db1/_utils.py
db1/_cli/__init__.py
db1/_cli/item.py
db1/_cli/main.py
db1/_protos/__init__.py
db1/_protos/item/__init__.py
db1/_protos/item/item_cr_0v1_pb2.py
db1/_protos/serializer/__init__.py
db1/_protos/serializer/serializer_pb2.py
db1/api/__init__.py
db1/api/_http_utils.py
db1/api/environment_vars.py
db1/api/exceptions.py
db1/api/_item/__init__.py
db1/api/_item/_utils.py
db1/api/_item/_rest/__init__.py
db1/api/_item/_rest/rest_functions.py
db1/api/_item/_rest/rest_requests.py
db1/serializer/__init__.py
db1/serializer/_encoder.py
db1/serializer/_serializer.py
db1/serializer/_types.py
db1-0.1.6.dist-info/LICENSE
db1-0.1.6.dist-info/METADATA
db1-0.1.6.dist-info/WHEEL
db1-0.1.6.dist-info/entry_points.txt
db1-0.1.6.dist-info/top_level.txt
db1-0.1.6.dist-info/RECORD
