Metadata-Version: 2.1
Name: db1
Version: 0.1.6
Summary: DB1 Python client
Home-page: https://db1.io
Author: db1
Author-email: hello@db1.io
Project-URL: Source Code, https://github.com/db1-io/db1-py
Classifier: Programming Language :: Python :: 3
Classifier: License :: OSI Approved :: MIT License
Classifier: Operating System :: POSIX :: Linux
Requires-Python: >=3.7
License-File: LICENSE
Requires-Dist: numpy
Requires-Dist: pyarrow
Requires-Dist: pandas
Requires-Dist: protobuf (>=3.20.0)
Requires-Dist: requests
Requires-Dist: websocket-client
